{
	"Wikipedia":
	{
		"URL":"https://en.wikipedia.org/wiki/Kurmanji",
		"Language codes":
		{
			"ISO 639-1":"ku",
			"ISO 639-3":"kmr",
			"Glottolot":"nort2641",
			"Linguasphere":"58-AAA-a",
		},
		"Official status":
		{
			"Official language in":["Kurdistan Region", "Rojava"],
			"Recognized minority language in":"Armenia",
			"Regulated by":""
		},
		"Info":
		{
			"Name":["Kurmanji","Northern Kurdish","کورمانجی","Kurmancî"],
			"Region":"Autochthonous to Kurdistan, Kurdish diaspora",
			"Language family":"Indo-European, Indo-Iranian, Iranian, Western, Northwestern, Kurdish",
			"Dialects":["Botani (Boti)","Marashi","Ashiti","Bayezidi","Hekari","Shamdinani","Badini","Shikaki","Silivi","Mihemedi"],
			"Writing system":["Hawar alphabet (Latin) in Turkey, Syria, Iraq and Iran", "Sorani alphabet (Arabic) in Iraw and Iran", "Cyrillic script in Russia and Armenia"]
		}
	}
}

